fastapi_cors/__init__.py
fastapi_cors/env.py
fastapi_cors/main.py
fastapi_cors/VERSION
fastapi_cors-0.0.5.dist-info/WHEEL
fastapi_cors-0.0.5.dist-info/METADATA
fastapi_cors-0.0.5.dist-info/licenses/LICENSE
fastapi_cors-0.0.5.dist-info/RECORD
